mesdi/__init__.py
mesdi/py.typed
mesdi-0.1.0.dist-info/LICENSE
mesdi-0.1.0.dist-info/METADATA
mesdi-0.1.0.dist-info/WHEEL
mesdi-0.1.0.dist-info/top_level.txt
mesdi-0.1.0.dist-info/RECORD
