Metadata-Version: 2.1
Name: mesdi
Version: 0.1.0
Summary: A data standard for working with event stream data
License: Apache-2.0
License-File: LICENSE
Requires-Dist: pyarrow >=12
Requires-Dist: jsonschema
